querypipz/__init__.py
querypipz/abc_.py
querypipz/director.py
querypipz/log.py
querypipz/queryer.py
querypipz/utils.py
querypipz/builder/__init__.py
querypipz/builder/builderlib.py
querypipz/factory/__init__.py
querypipz/factory/agent.py
querypipz/factory/index.py
querypipz/factory/postprocessor.py
querypipz/factory/query_pipeline.py
querypipz/factory/reader.py
querypipz/factory/retriver.py
querypipz/factory/store.py
querypipz/factory/store_utils.py
querypipz/factory/ingestion_pipeline/__init__.py
querypipz/factory/ingestion_pipeline/cleaner.py
querypipz/factory/ingestion_pipeline/embedding.py
querypipz/factory/ingestion_pipeline/extractor.py
querypipz/factory/ingestion_pipeline/graph_extractor.py
querypipz/factory/ingestion_pipeline/llm.py
querypipz/factory/ingestion_pipeline/node_parser.py
querypipz/factory/ingestion_pipeline/splitter.py
querypipz-0.1.22.dist-info/METADATA
querypipz-0.1.22.dist-info/WHEEL
querypipz-0.1.22.dist-info/top_level.txt
querypipz-0.1.22.dist-info/RECORD
