Metadata-Version: 2.4
Name: querypipz
Version: 0.1.22
Summary: 提供使用llama-index的适配器接口
Requires-Python: >=3.10
Requires-Dist: llama-index[all]>=0.12.31
Requires-Dist: llama-index-readers-file>=0.4.7
Requires-Dist: llama-index-readers-github>=0.6.1
Requires-Dist: llama-index-core>=0.12.31
Requires-Dist: llama-index-readers-database>=0.4.0
Requires-Dist: llama-index-vector-stores-faiss>=0.4.0
Requires-Dist: llama-index-graph-stores-neo4j>=0.4.6
Requires-Dist: llama-index-graph-stores-memgraph>=0.3.1
Requires-Dist: llama-index-graph-stores-nebula>=0.4.2
Requires-Dist: llama-index-vector-stores-pinecone>=0.4.5
Requires-Dist: pinecone>=6.0.2
Requires-Dist: redis>=6.2.0
Requires-Dist: pypdf2>=3.0.1
Requires-Dist: promptlibz==0.2.10
Requires-Dist: toolsz==1.0.1
Requires-Dist: toml==0.10.2
Requires-Dist: llama-index-llms-openrouter>=0.3.2
